[
  {
    "model": "monitor.item",
    "pk": 1,
    "fields": {
      "ctime": "2001-01-01T00:00:00Z",
      "utime": "2001-01-01T00:00:00Z",
      "mon_title": "账户登陆",
      "mon_type": 1,
      "mon_trigger": "0 */5 * * * ? *",
      "mon_trigger_desc": "轮询每隔5分钟",
      "mon_desc": "模拟用户登陆，如果无法登陆，则告警level：1",
      "mon_status": 1
    }
  },
  {
    "model": "monitor.item",
    "pk": 2,
    "fields": {
      "ctime": "2001-01-01T00:00:00Z",
      "utime": "2001-01-01T00:00:00Z",
      "mon_title": "当日注册用户",
      "mon_type": 2,
      "mon_trigger": "0 */30 10-23 * * ? *",
      "mon_trigger_desc": "每天从10:00-00:00，每0.5小时查询一次",
      "mon_desc": "如果每小时注册量=0, level=1; 注册量<昨天同比30%，level=2",
      "mon_status": 1
    }
  },
  {
    "model": "monitor.item",
    "pk": 3,
    "fields": {
      "ctime": "2001-01-01T00:00:00Z",
      "utime": "2001-01-01T00:00:00Z",
      "mon_title": "当日放款金额",
      "mon_type": 2,
      "mon_trigger": "0 55 9-23/1 * * ? *",
      "mon_trigger_desc": "每天从10:00-00:00，每0.5小时查询一次",
      "mon_desc": "如果放款量=0, level=1; 放款量<昨天同比50%，level=2",
      "mon_status": 1
    }
  },
  {
    "model": "monitor.item",
    "pk": 4,
    "fields": {
      "ctime": "2001-01-01T00:00:00Z",
      "utime": "2001-01-01T00:00:00Z",
      "mon_title": "当日回款",
      "mon_type": 2,
      "mon_trigger": "0 56 12-23/1 * * ? *",
      "mon_trigger_desc": "每天从12:00-00:00，每个小时查询一次",
      "mon_desc": "如果回款量=0, level=1; 回款率<昨天同比30%，level=2；23:00时的回款率<60%, level=2;",
      "mon_status": 1
    }
  },
  {
    "model": "monitor.item",
    "pk": 5,
    "fields": {
      "ctime": "2001-01-01T00:00:00Z",
      "utime": "2000-01-01T00:00:00Z",
      "mon_title": "还款短信和语音提醒",
      "mon_type": 2,
      "mon_trigger": "0 30 9 * * ? *",
      "mon_trigger_desc": "每天9:30检查",
      "mon_desc": "短信（T、T-1）成功率0.8；语音首次成功率0.2，level=2;",
      "mon_status": 1
    }
  },
  {
    "model": "monitor.item",
    "pk": 6,
    "fields": {
      "ctime": "2001-01-01T00:00:00Z",
      "utime": "2001-01-01T00:00:00Z",
      "mon_title": "催收案件分配",
      "mon_type": 2,
      "mon_trigger": "0 30 9 * * ? *",
      "mon_trigger_desc": "每天9:30检查",
      "mon_desc": "如果没有催收案件分配，level=2",
      "mon_status": 1
    }
  },
  {
    "model": "monitor.item",
    "pk": 7,
    "fields": {
      "ctime": "2001-01-01T00:00:00Z",
      "utime": "2001-01-01T00:00:00Z",
      "mon_title": "账户余额",
      "mon_type": 2,
      "mon_trigger": "0 0 */1 * * ? *",
      "mon_trigger_desc": "每1个小时检查一次",
      "mon_desc": "如果当前易宝账户余额<昨天同期下2个小时放款量的1.5倍，则level 1",
      "mon_status": 1
    }
  },
  {
    "model": "monitor.item",
    "pk": 8,
    "fields": {
      "ctime": "2001-01-01T00:00:00Z",
      "utime": "2001-01-01T00:00:00Z",
      "mon_title": "通过率检查",
      "mon_type": 3,
      "mon_trigger": "0 */30 9-23 * ? *",
      "mon_trigger_desc": "每天从9:00开始每0.5小时查询一次",
      "mon_desc": "当日的注册数>50的情况下，注册放款率或者审核通过率=0，level=1；9:00~12:00：注册放款率<3.5%或者审核通过率<10%, level=2；12:00以后注册放款率<5%或者审核通过率<10%, level=2",
      "mon_status": 1
    }
  },
  {
    "model": "monitor.item",
    "pk": 9,
    "fields": {
      "ctime": "2001-01-01T00:00:00Z",
      "utime": "2001-01-01T00:00:00Z",
      "mon_title": "failReason异常检查",
      "mon_type": 3,
      "mon_trigger": "0 0 9-23/1 * * ? *",
      "mon_trigger_desc": "每天从9:00开始每1小时查询一次",
      "mon_desc": "failreaon占比>30%，level=2;",
      "mon_status": 1
    }
  },
  {
    "model": "monitor.item",
    "pk": 10,
    "fields": {
      "ctime": "2001-01-01T00:00:00Z",
      "utime": "2001-01-01T00:00:00Z",
      "mon_title": "通过借款率监控",
      "mon_type": 3,
      "mon_trigger": "0 0 9-23/1 * * ? *",
      "mon_trigger_desc": "每天从9:00开始每1小时查询一次",
      "mon_desc": "当日的某个渠道的通过数>=10的情况下，借款率>=90%，level=2",
      "mon_status": 1,
      "free_date": "2018-12-04",
      "free_data": ",明特量化,菠萝贷-2,"
    }
  },
  {
    "model": "monitor.item",
    "pk": 11,
    "fields": {
      "ctime": "2001-01-01T00:00:00Z",
      "utime": "2001-01-01T00:00:00Z",
      "mon_title": "渠道首逾监控",
      "mon_type": 3,
      "mon_trigger": "0 1 0 * * ? *",
      "mon_trigger_desc": "每天00:01查询一次",
      "mon_desc": "昨日应还的某个渠道的借款数>=8，并且自然还款率<=50%，level=2",
      "mon_status": 1
    }
  },
  {
    "model": "monitor.item",
    "pk": 12,
    "fields": {
      "ctime": "2001-01-01T00:00:00Z",
      "utime": "2001-01-01T00:00:00Z",
      "mon_title": "接口调用检查",
      "mon_type": 4,
      "mon_trigger": "0 */30 * * * ? *",
      "mon_trigger_desc": "每0.5小时检查一次",
      "mon_desc": "每个第三方接口调用最近的0.5个小时的调用里有错误，且最后一次调用错误，则level=1；如果有错误，但最后一次调用ok，则level=2",
      "mon_status": 1
    }
  }
]